cmsplugin_eviscape
