Metadata-Version: 1.1
Name: cmsplugin-eviscape
Version: 0.8.1
Summary: An Eviscape extension for Django CMS
Home-page: https://github.com/TESOBE/cmsplugin_eviscape
Author: Tim Kleinschmidt, Tobias Pfeiffer
Author-email: tim@tesobe.com, tobias@tesobe.com
License: BSD
Platform: OS Independent
Classifier: Development Status :: 4 - Beta
Classifier: Framework :: Django
Classifier: Intended Audience :: Developers
Classifier: License :: OSI Approved :: BSD License
Classifier: Operating System :: OS Independent
Classifier: Programming Language :: Python
Classifier: Topic :: Internet :: WWW/HTTP
Classifier: Topic :: Internet :: WWW/HTTP :: Dynamic Content
